<PAMDataset>
  <Metadata>
    <MDI key="DataType">Generic</MDI>
  </Metadata>
  <PAMRasterBand band="1">
    <Description>Band_1</Description>
    <Histograms>
      <HistItem>
        <HistMin>34.73166656494141</HistMin>
        <HistMax>2085.356689453125</HistMax>
        <BucketCount>256</BucketCount>
        <IncludeOutOfRange>1</IncludeOutOfRange>
        <Approximate>0</Approximate>
        <HistCounts>8|11|12|9|16|32|36|56|67|230|128|93|65|57|56|78|106|114|116|91|56|69|69|45|35|29|25|30|31|37|65|456|356|72|111|98|126|93|73|91|79|67|54|41|48|21|33|35|26|27|22|30|20|42|34|48|33|40|46|36|36|36|42|34|36|40|32|26|24|31|32|33|29|13|11|22|18|19|13|17|23|20|25|29|29|38|25|34|37|28|33|36|36|45|34|38|33|32|37|27|24|20|24|19|17|38|21|19|20|27|19|22|19|21|25|26|16|22|17|17|25|29|22|24|28|22|19|14|14|16|17|11|12|14|12|7|4|7|9|8|9|6|7|10|6|5|14|7|7|11|6|8|7|3|9|6|6|9|11|6|6|10|8|6|9|7|4|13|4|5|2|4|4|1|0|5|4|2|2|1|2|1|3|4|5|5|6|5|0|4|7|4|2|3|6|2|2|3|2|5|5|4|5|0|1|4|2|1|0|0|4|1|2|3|2|3|1|2|1|1|0|3|0|1|2|0|0|0|0|0|0|1|0|1|2|1|0|0|1|0|0|1|1|0|2|1|0|0|0|0|0|1|0|0|0|1</HistCounts>
      </HistItem>
    </Histograms>
    <Metadata>
      <MDI key="BandName">Band_1</MDI>
      <MDI key="RepresentationType">ATHEMATIC</MDI>
      <MDI key="STATISTICS_COVARIANCES">131320.7162503938</MDI>
      <MDI key="STATISTICS_EXCLUDEDVALUES"></MDI>
      <MDI key="STATISTICS_MAXIMUM">2085.3566894531</MDI>
      <MDI key="STATISTICS_MEAN">492.47722980673</MDI>
      <MDI key="STATISTICS_MINIMUM">34.731666564941</MDI>
      <MDI key="STATISTICS_SKIPFACTORX">1</MDI>
      <MDI key="STATISTICS_SKIPFACTORY">1</MDI>
      <MDI key="STATISTICS_STDDEV">362.38200320986</MDI>
    </Metadata>
  </PAMRasterBand>
</PAMDataset>
